{ 
    "_id" : ObjectId("5c8f352404599d0f57179101"), 
    "ProductID" : "040010001", 
    "ProductName" : "星巴克®凤舞祥云综合咖啡豆", 
    "ProductImage" : "south-of-the-clouds.jpg", 
    "Category" : "Coffee", 
    "SubTypes" : "baking-M"
}
{ 
    "_id" : ObjectId("5c8f352404599d0f57179102"), 
    "ProductID" : "040010002", 
    "ProductName" : "星巴克®派克市场烘焙咖啡豆", 
    "ProductImage" : "pike-place-roast-coffee-beans.png", 
    "Category" : "Coffee", 
    "SubTypes" : "baking-M"
}
{ 
    "_id" : ObjectId("5c8f352404599d0f57179103"), 
    "ProductID" : "040010003", 
    "ProductName" : "星巴克®肯亚咖啡豆", 
    "ProductImage" : "kenya-coffee-beans.png", 
    "Category" : "Coffee", 
    "SubTypes" : "baking-M"
}
{ 
    "_id" : ObjectId("5c8f352404599d0f57179104"), 
    "ProductID" : "040010004", 
    "ProductName" : "星巴克®首选咖啡豆", 
    "ProductImage" : "house-blend-coffee-beans.png", 
    "Category" : "Coffee", 
    "SubTypes" : "baking-M"
}
{ 
    "_id" : ObjectId("5c8f352404599d0f57179105"), 
    "ProductID" : "040010005", 
    "ProductName" : "星巴克®危地马拉安提瓜咖啡豆", 
    "ProductImage" : "guatemala-antigua-coffee-beans.png", 
    "Category" : "Coffee", 
    "SubTypes" : "baking-M"
}
{ 
    "_id" : ObjectId("5c8f352404599d0f57179106"), 
    "ProductID" : "040010006", 
    "ProductName" : "星巴克®埃塞俄比亚咖啡豆", 
    "ProductImage" : "ethiopia-coffee-beans.png", 
    "Category" : "Coffee", 
    "SubTypes" : "baking-M"
}
{ 
    "_id" : ObjectId("5c8f352404599d0f57179107"), 
    "ProductID" : "040010007", 
    "ProductName" : "星巴克®哥伦比亚咖啡豆", 
    "ProductImage" : "colombia.jpg", 
    "Category" : "Coffee", 
    "SubTypes" : "baking-M"
}
{ 
    "_id" : ObjectId("5c8f352404599d0f57179108"), 
    "ProductID" : "040010008", 
    "ProductName" : "星巴克®早餐综合咖啡豆", 
    "ProductImage" : "breakfast-blend-coffee-beans.png", 
    "Category" : "Coffee", 
    "SubTypes" : "baking-M"
}
{ 
    "_id" : ObjectId("5c8f352404599d0f57179109"), 
    "ProductID" : "040020001", 
    "ProductName" : "星巴克®苏门答腊咖啡豆", 
    "ProductImage" : "sumatra-coffee-beans.png", 
    "Category" : "Coffee", 
    "SubTypes" : "baking-D"
}
{ 
    "_id" : ObjectId("5c8f352404599d0f57179110"), 
    "ProductID" : "040020002", 
    "ProductName" : "星巴克®低因祥龙综合咖啡豆", 
    "ProductImage" : "komodo-dragon-blend-coffee-beans.png", 
    "Category" : "Coffee", 
    "SubTypes" : "baking-D"
}
{ 
    "_id" : ObjectId("5c8f352404599d0f57179111"), 
    "ProductID" : "040020003", 
    "ProductName" : "星巴克®意式烘焙咖啡豆", 
    "ProductImage" : "italian-roast-coffee-beans.png", 
    "Category" : "Coffee", 
    "SubTypes" : "baking-D"
}
{ 
    "_id" : ObjectId("5c8f352404599d0f57179112"), 
    "ProductID" : "040020004", 
    "ProductName" : "星巴克®浓缩烘焙咖啡豆", 
    "ProductImage" : "espresso-roast-coffee-beans.png", 
    "Category" : "Coffee", 
    "SubTypes" : "baking-D"
}
{ 
    "_id" : ObjectId("5c8f352404599d0f57179113"), 
    "ProductID" : "040020005", 
    "ProductName" : "星巴克®佛罗娜咖啡豆", 
    "ProductImage" : "caffe-verona-coffee-beans.png", 
    "Category" : "Coffee", 
    "SubTypes" : "baking-D"
}
{ 
    "_id" : ObjectId("5c8f352404599d0f57179114"), 
    "ProductID" : "040030001", 
    "ProductName" : "星巴克VIA®香草拿铁风味免煮咖啡固体饮料", 
    "ProductImage" : "via-vanilla-latte.jpg", 
    "Category" : "Coffee", 
    "SubTypes" : "via-dairy"
}
{ 
    "_id" : ObjectId("5c8f352404599d0f57179115"), 
    "ProductID" : "040030002", 
    "ProductName" : "星巴克VIA®焦糖拿铁风味免煮咖啡固体饮料", 
    "ProductImage" : "via-caramel-latte.jpg", 
    "Category" : "Coffee", 
    "SubTypes" : "via-dairy"
}
{ 
    "_id" : ObjectId("5c8f352404599d0f57179116"), 
    "ProductID" : "040030003", 
    "ProductName" : "星巴克VIA®摩卡风味免煮咖啡固体饮料", 
    "ProductImage" : "via-caffe-mocha.jpg", 
    "Category" : "Coffee", 
    "SubTypes" : "via-dairy"
}
{ 
    "_id" : ObjectId("5c8f352404599d0f57179117"), 
    "ProductID" : "040040001", 
    "ProductName" : "星巴克VIA®意式烘焙免煮咖啡", 
    "ProductImage" : "via-italian-roast.jpg", 
    "Category" : "Coffee", 
    "SubTypes" : "via-black"
}
{ 
    "_id" : ObjectId("5c8f352404599d0f57179118"), 
    "ProductID" : "040040002", 
    "ProductName" : "星巴克VIA®哥伦比亚免煮咖啡", 
    "ProductImage" : "via-colombia.jpg", 
    "Category" : "Coffee", 
    "SubTypes" : "via-black"
}
{ 
    "_id" : ObjectId("5c8f352404599d0f57179119"), 
    "ProductID" : "040040001", 
    "ProductName" : "星巴克臻选™ 日晒巴西格兰玛瀑布农场", 
    "ProductImage" : "reserve-sun-dried-brazil-cachoeirab-grama-farm.jpg", 
    "Category" : "Coffee", 
    "SubTypes" : "selection"
}
{ 
    "_id" : ObjectId("5c8f352404599d0f57179120"), 
    "ProductID" : "040040002", 
    "ProductName" : "星巴克臻选™ 夏威夷卡乌咖啡豆", 
    "ProductImage" : "reserve-hawaii-kau.jpg", 
    "Category" : "Coffee", 
    "SubTypes" : "selection"
}
{ 
    "_id" : ObjectId("5c8f352404599d0f57179121"), 
    "ProductID" : "040040003", 
    "ProductName" : "星巴克臻选™ 哥伦比亚佩德雷加尔", 
    "ProductImage" : "reserve-colombia-pedregal.jpg", 
    "Category" : "Coffee", 
    "SubTypes" : "selection"
}
{ 
    "_id" : ObjectId("5c8f352404599d0f57179122"), 
    "ProductID" : "040040004", 
    "ProductName" : "星巴克臻选™ 臻选2018圣诞专享咖啡豆", 
    "ProductImage" : "reserve-christmas-blend-2018.jpg", 
    "Category" : "Coffee", 
    "SubTypes" : "selection"
}
{ 
    "_id" : ObjectId("5c8f352404599d0f57179123"), 
    "ProductID" : "040050001", 
    "ProductName" : "星巴克ORIGAMI™便携式滴滤咖啡（研磨咖啡粉）星巴克®派克市场烘焙咖啡系列", 
    "ProductImage" : "origami-pike-place.jpg", 
    "Category" : "Coffee", 
    "SubTypes" : "origami-M"
}
{ 
    "_id" : ObjectId("5c8f352404599d0f57179124"), 
    "ProductID" : "040060001", 
    "ProductName" : "星巴克ORIGAMI™便携式滴滤咖啡（研磨咖啡粉）星巴克®佛罗娜烘焙咖啡系列", 
    "ProductImage" : "origami-verona.jpg", 
    "Category" : "Coffee", 
    "SubTypes" : "origami-D"
}
